{"url":"n.a.","type":"cable","notes":null,"length":"3,100 km","rfs":"1992","name":"Eurafrica","owners":"France Telecom,  Portugal Telecom,  Maroc Telecom,  Cable & Wireless Worldwide,  Tata Communications,  KPN,  Rostelecom,  Telekom Austria,  BT","description":"[{\"latitude\":\"33.586984\",\"longitude\":\"-7.611113\",\"name\":\"Casablanca, Morocco\",\"id\":\"3256\"},{\"latitude\":\"32.647263\",\"longitude\":\"-16.905068\",\"name\":\"Funchal, Portugal\",\"id\":\"5935\"},{\"latitude\":\"38.442690\",\"longitude\":\"-9.102760\",\"name\":\"Sesimbra, Portugal\",\"id\":\"5934\"},{\"latitude\":\"47.135580\",\"longitude\":\"-2.105151\",\"name\":\"St. Hilaire, France\",\"id\":\"5834\"}]","id":"1127"}
