{"type":"cable","length":"13,000 km","rfs":"February 2003","owners":"Cable & Wireless Worldwide,  Alcatel-Lucent","url":"http://www.apollo-scs.com","name":"Apollo","description":"[{\"longitude\":\"-4.544398\",\"name\":\"Bude, United Kingdom\",\"latitude\":\"50.828106\",\"id\":\"4554\"},{\"longitude\":\"-3.459920\",\"name\":\"Lannion, France\",\"latitude\":\"48.730224\",\"id\":\"5837\"},{\"longitude\":\"-74.047060\",\"name\":\"Manasquan, New Jersey, United States\",\"latitude\":\"40.123365\",\"id\":\"3686\"},{\"longitude\":\"-72.872234\",\"name\":\"Shirley, New York, United States\",\"latitude\":\"40.800273\",\"id\":\"3783\"}]","id":"1213"}
