{"type":"cable","length":"6,700 km","rfs":"March 2009","owners":"Tata Communications","name":"Tata TGN-Intra Asia (TGN-IA)","url":"http://www.tatacommunications.com","description":"[{\"latitude\":\"18.409411\",\"longitude\":\"121.514047\",\"name\":\"Ballesteros, Philippines\",\"id\":\"8541\"},{\"latitude\":\"1.389040\",\"longitude\":\"103.987023\",\"name\":\"Changi, Singapore\",\"id\":\"5937\"},{\"latitude\":\"22.249405\",\"longitude\":\"114.184008\",\"name\":\"Deep Water Bay, Hong Kong\",\"id\":\"5853\"},{\"latitude\":\"10.341931\",\"longitude\":\"107.079236\",\"name\":\"Vung Tau, Vietnam\",\"id\":\"6013\"}]","id":"1534"}
