{"type":"cable","length":"15,000 km","rfs":"February 2011","owners":"AT&T,  Verizon Business,  DU,  airtel (Bharti),  Omantel,  Saudi Telecom,  BT,  Cable & Wireless Worldwide,  Telkom South Africa,  Portugal Telecom,  Djibouti Telecom,  Telecom Egypt,  MTN Group,  Gibtelecom,  Libyan PTT (GPTC),  Bharat Sanchar Nigam Ltd. (BSNL),  Mauritius Telecom","url":"http://www.europeindiagateway.com","name":"Europe India Gateway (EIG)","description":"[{\"longitude\":\"29.702539\",\"name\":\"Abu Talat, Egypt\",\"latitude\":\"31.071894\",\"id\":\"9485\"},{\"longitude\":\"58.004373\",\"name\":\"Barka, Oman\",\"latitude\":\"23.679414\",\"id\":\"8947\"},{\"longitude\":\"-4.544398\",\"name\":\"Bude, United Kingdom\",\"latitude\":\"50.828106\",\"id\":\"4554\"},{\"longitude\":\"43.148039\",\"name\":\"Djibouti City, Djibouti\",\"latitude\":\"11.594657\",\"id\":\"4177\"},{\"longitude\":\"56.333737\",\"name\":\"Fujairah, United Arab Emirates\",\"latitude\":\"25.121671\",\"id\":\"5962\"},{\"longitude\":\"-5.347693\",\"name\":\"Gibraltar, Gibraltar\",\"latitude\":\"36.155981\",\"id\":\"8948\"},{\"longitude\":\"39.182762\",\"name\":\"Jeddah, Saudi Arabia\",\"latitude\":\"21.481246\",\"id\":\"4361\"},{\"longitude\":\"7.417686\",\"name\":\"Monaco, Monaco\",\"latitude\":\"43.732570\",\"id\":\"3255\"},{\"longitude\":\"72.875866\",\"name\":\"Mumbai, India\",\"latitude\":\"19.075779\",\"id\":\"3212\"},{\"longitude\":\"-9.102760\",\"name\":\"Sesimbra, Portugal\",\"latitude\":\"38.442690\",\"id\":\"5934\"},{\"longitude\":\"13.187314\",\"name\":\"Tripoli, Libya\",\"latitude\":\"32.877350\",\"id\":\"4271\"},{\"longitude\":\"32.649894\",\"name\":\"Zafarana, Egypt\",\"latitude\":\"29.116662\",\"id\":\"9486\"}]","id":"1580"}
