{"type":"cable","notes":null,"length":"10,000 km","rfs":"Q4 2014","owners":"eFive Telecoms","name":"South Atlantic Express (SAEx)","description":"[{\"latitude\":\"-8.776624\",\"longitude\":\"13.372327\",\"name\":\"Cacuaco, Angola\",\"id\":\"5775\"},{\"latitude\":\"-33.919086\",\"longitude\":\"18.421981\",\"name\":\"Cape Town, South Africa\",\"id\":\"3921\"},{\"latitude\":\"-3.718838\",\"longitude\":\"-38.542979\",\"name\":\"Fortaleza, Brazil\",\"id\":\"3347\"},{\"latitude\":\"-15.922152\",\"longitude\":\"-5.704668\",\"name\":\"Jamestown, Saint Helena\",\"id\":\"10722\"},{\"latitude\":\"-28.950645\",\"longitude\":\"31.757858\",\"name\":\"Mtunzini, South Africa\",\"id\":\"5942\"}]","id":"1669","url":"http://efive.co.za"}
